semantic_sh/__init__.py
semantic_sh/semantic_sh.py
semantic_sh-1.4.dist-info/LICENSE.txt
semantic_sh-1.4.dist-info/METADATA
semantic_sh-1.4.dist-info/WHEEL
semantic_sh-1.4.dist-info/top_level.txt
semantic_sh-1.4.dist-info/RECORD
