Metadata-Version: 2.1
Name: semantic-sh
Version: 1.4
Summary: semantic-sh is a SimHash implementation to detect and group similar texts by taking power of word vectors and transformer-based language models such as BERT.
Home-page: UNKNOWN
Author: Kerem Zaman
Author-email: UNKNOWN
License: MIT
Platform: UNKNOWN
